[
  {
    "name": "George Orwell",
    "about": "George Orwell vlastn\u00EDm jm\u00E9nem Eric Arthur Blair byl britsk\u00FD novin\u00E1\u0159, esejista a spisovatel demokratick\u00E9 levicov\u00E9 orientace. Sv\u011Btovou popularitu si z\u00EDskaly jeho alegorick\u00E9 antiutopick\u00E9 rom\u00E1ny Farma zv\u00ED\u0159at a 1984 popisuj\u00EDc\u00ED nehum\u00E1nnost totalitn\u00EDch ideologi\u00ED.",
    "style": "",
    "friends": "Ernest Hemingway"
  },
  {
    "name": "Karel Čapek",
    "about": "Krog vs. Krüg",
    "style": "Realimus",
    "friends": "Josef Čapek"
  }
]